stt_F/Ruhani_runner.py
stt_F/__init__.py
stt_F/index.html
stt_F/script.js
stt_F/styles.css
stt_f-1.0.dist-info/METADATA
stt_f-1.0.dist-info/WHEEL
stt_f-1.0.dist-info/top_level.txt
stt_f-1.0.dist-info/RECORD
