Metadata-Version: 2.4
Name: stt_F
Version: 1.0
Summary: Offline speech-to-text tool using browser frontend and Python backend
Author: Farhan Raza Shaikh
Author-email: itsnobody@zohomail.in
Classifier: Programming Language :: Python :: 3
Classifier: Operating System :: OS Independent
Requires-Python: >=3.6
Dynamic: author
Dynamic: author-email
Dynamic: classifier
Dynamic: description
Dynamic: description-content-type
Dynamic: requires-python
Dynamic: summary
